{
  "version": "5",
  "dialect": "pg",
  "entries": [
    {
      "idx": 0,
      "version": "5",
      "when": 1694965953888,
      "tag": "0000_complex_triathlon",
      "breakpoints": true
    },
    {
      "idx": 1,
      "version": "5",
      "when": 1694966266949,
      "tag": "0001_heavy_thunderbird",
      "breakpoints": true
    },
    {
      "idx": 2,
      "version": "5",
      "when": 1694967265844,
      "tag": "0002_blue_echo",
      "breakpoints": true
    },
    {
      "idx": 3,
      "version": "5",
      "when": 1694979810915,
      "tag": "0003_ordinary_black_bird",
      "breakpoints": true
    }
  ]
}